[{"name":"NETWORK_GET_GANG_ID","hash":"0x901E0DC25080C8B9","build":"1207","ret":"Any","comment":"","research":null,"params":[{"name":"player","type":"Player","out":false}],"lua":"-- 0x901E0DC25080C8B9 · build 1207\nlocal player = PlayerId()\nlocal result = NetworkGetGangId(player)"},{"name":"NETWORK_GET_GANG_LEADER","hash":"0x4BE6C13A45CCA8EC","build":"1207","ret":"Player","comment":"","research":null,"params":[{"name":"gangId","type":"Any","out":false}],"lua":"-- 0x4BE6C13A45CCA8EC · build 1207\nlocal gangId = 0\nlocal result = NetworkGetGangLeader(gangId)"},{"name":"NETWORK_GET_NUM_GANG_MEMBERS","hash":"0x149A2751AB66AC02","build":"1207","ret":"int","comment":"","research":null,"params":[{"name":"gangId","type":"Any","out":false}],"lua":"-- 0x149A2751AB66AC02 · build 1207\nlocal gangId = 0\nlocal result = NetworkGetNumGangMembers(gangId)"},{"name":"NETWORK_IS_GANG_ACTIVE","hash":"0x0F99F6436528A089","build":"1207","ret":"BOOL","comment":"","research":null,"params":[{"name":"gangId","type":"Any","out":false}],"lua":"-- 0x0F99F6436528A089 · build 1207\nlocal gangId = 0\nlocal result = NetworkIsGangActive(gangId)"},{"name":"NETWORK_IS_GANG_ID_VALID","hash":"0xD6F6ACF4392187FB","build":"1207","ret":"BOOL","comment":"","research":null,"params":[{"name":"gangId","type":"Any","out":false}],"lua":"-- 0xD6F6ACF4392187FB · build 1207\nlocal gangId = 0\nlocal result = NetworkIsGangIdValid(gangId)"},{"name":"NETWORK_IS_GANG_IN_SESSION","hash":"0x93A91A351A07360E","build":"1207","ret":"BOOL","comment":"","research":null,"params":[{"name":"gangId","type":"Any","out":false}],"lua":"-- 0x93A91A351A07360E · build 1207\nlocal gangId = 0\nlocal result = NetworkIsGangInSession(gangId)"},{"name":"NETWORK_IS_GANG_LEADER","hash":"0x424B17A7DC5C90BC","build":"1207","ret":"BOOL","comment":"","research":null,"params":[{"name":"player","type":"Player","out":false}],"lua":"-- 0x424B17A7DC5C90BC · build 1207\nlocal player = PlayerId()\nlocal result = NetworkIsGangLeader(player)"},{"name":"NETWORK_IS_IN_SAME_GANG","hash":"0x3F59FE6F37869576","build":"1207","ret":"BOOL","comment":"","research":null,"params":[{"name":"player1","type":"Player","out":false},{"name":"player2","type":"Player","out":false}],"lua":"-- 0x3F59FE6F37869576 · build 1207\nlocal player1 = PlayerId()\nlocal player2 = PlayerId()\nlocal result = NetworkIsInSameGang(player1, player2)"},{"name":"_0x0E5C9FB9ED5DFF1C","hash":"0x0E5C9FB9ED5DFF1C","build":"1207","ret":"Any","comment":"","research":null,"params":[{"name":"p0","type":"Any","out":false}],"lua":"-- 0x0E5C9FB9ED5DFF1C · build 1207\nlocal p0 = 0\nlocal result = Citizen.InvokeNative(0x0E5C9FB9ED5DFF1C, p0, Citizen.ResultAsInteger())"},{"name":"_0x1F11702DDBD915C6","hash":"0x1F11702DDBD915C6","build":"1207","ret":"Any","comment":"","research":null,"params":[{"name":"p0","type":"Any","out":false},{"name":"p1","type":"Any","out":false}],"lua":"-- 0x1F11702DDBD915C6 · build 1207\nlocal p0 = 0\nlocal p1 = 0\nlocal result = Citizen.InvokeNative(0x1F11702DDBD915C6, p0, p1, Citizen.ResultAsInteger())"},{"name":"_0x2F7EB8B6F6AFE79C","hash":"0x2F7EB8B6F6AFE79C","build":"1207","ret":"Any","comment":"","research":null,"params":[{"name":"p0","type":"Any","out":false}],"lua":"-- 0x2F7EB8B6F6AFE79C · build 1207\nlocal p0 = 0\nlocal result = Citizen.InvokeNative(0x2F7EB8B6F6AFE79C, p0, Citizen.ResultAsInteger())"},{"name":"_0x3ADC71A66356D706","hash":"0x3ADC71A66356D706","build":"1207","ret":"Any","comment":"","research":null,"params":[],"lua":"-- 0x3ADC71A66356D706 · build 1207\nlocal result = Citizen.InvokeNative(0x3ADC71A66356D706, Citizen.ResultAsInteger())"},{"name":"_0x48D82C83987E18E4","hash":"0x48D82C83987E18E4","build":"1207","ret":"Any","comment":"","research":null,"params":[{"name":"p0","type":"Any","out":false}],"lua":"-- 0x48D82C83987E18E4 · build 1207\nlocal p0 = 0\nlocal result = Citizen.InvokeNative(0x48D82C83987E18E4, p0, Citizen.ResultAsInteger())"},{"name":"_0x51C5EF47086AA0D7","hash":"0x51C5EF47086AA0D7","build":"1207","ret":"Any","comment":"","research":null,"params":[],"lua":"-- 0x51C5EF47086AA0D7 · build 1207\nlocal result = Citizen.InvokeNative(0x51C5EF47086AA0D7, Citizen.ResultAsInteger())"},{"name":"_0x53A94294FDDCF98C","hash":"0x53A94294FDDCF98C","build":"1207","ret":"Any","comment":"","research":null,"params":[{"name":"p0","type":"Any","out":false},{"name":"p1","type":"Any","out":false}],"lua":"-- 0x53A94294FDDCF98C · build 1207\nlocal p0 = 0\nlocal p1 = 0\nlocal result = Citizen.InvokeNative(0x53A94294FDDCF98C, p0, p1, Citizen.ResultAsInteger())"},{"name":"_0x6102830F764B3DE1","hash":"0x6102830F764B3DE1","build":"1207","ret":"BOOL","comment":"","research":null,"params":[{"name":"player","type":"Player","out":false}],"lua":"-- 0x6102830F764B3DE1 · build 1207\nlocal player = PlayerId()\nlocal result = Citizen.InvokeNative(0x6102830F764B3DE1, player, Citizen.ResultAsInteger())"},{"name":"_0x644E02F24F9D4E98","hash":"0x644E02F24F9D4E98","build":"1207","ret":"Any","comment":"","research":null,"params":[{"name":"p0","type":"Any","out":false},{"name":"p1","type":"Any","out":false}],"lua":"-- 0x644E02F24F9D4E98 · build 1207\nlocal p0 = 0\nlocal p1 = 0\nlocal result = Citizen.InvokeNative(0x644E02F24F9D4E98, p0, p1, Citizen.ResultAsInteger())"},{"name":"_0x7933754F260B428A","hash":"0x7933754F260B428A","build":"1207","ret":"Any","comment":"","research":null,"params":[{"name":"player","type":"Player","out":false}],"lua":"-- 0x7933754F260B428A · build 1207\nlocal player = PlayerId()\nlocal result = Citizen.InvokeNative(0x7933754F260B428A, player, Citizen.ResultAsInteger())"},{"name":"_0x7BAA30C9BBE8AEE7","hash":"0x7BAA30C9BBE8AEE7","build":"1207","ret":"Any","comment":"","research":null,"params":[{"name":"p0","type":"Any","out":false},{"name":"p1","type":"Any","out":false}],"lua":"-- 0x7BAA30C9BBE8AEE7 · build 1207\nlocal p0 = 0\nlocal p1 = 0\nlocal result = Citizen.InvokeNative(0x7BAA30C9BBE8AEE7, p0, p1, Citizen.ResultAsInteger())"},{"name":"_0xA9CEAE8D6637FBAD","hash":"0xA9CEAE8D6637FBAD","build":"1207","ret":"void","comment":"","research":null,"params":[{"name":"p0","type":"Any","out":false}],"lua":"-- 0xA9CEAE8D6637FBAD · build 1207\nlocal p0 = 0\nCitizen.InvokeNative(0xA9CEAE8D6637FBAD, p0)"},{"name":"_0xAD22AB64FA428DF3","hash":"0xAD22AB64FA428DF3","build":"1207","ret":"void","comment":"","research":null,"params":[{"name":"p0","type":"Any","out":false}],"lua":"-- 0xAD22AB64FA428DF3 · build 1207\nlocal p0 = 0\nCitizen.InvokeNative(0xAD22AB64FA428DF3, p0)"},{"name":"_0xAFD3599A3CC5637D","hash":"0xAFD3599A3CC5637D","build":"1207","ret":"Any","comment":"","research":null,"params":[],"lua":"-- 0xAFD3599A3CC5637D · build 1207\nlocal result = Citizen.InvokeNative(0xAFD3599A3CC5637D, Citizen.ResultAsInteger())"},{"name":"_0xB22B1D9F74095382","hash":"0xB22B1D9F74095382","build":"1207","ret":"void","comment":"","research":null,"params":[{"name":"p0","type":"Any","out":false}],"lua":"-- 0xB22B1D9F74095382 · build 1207\nlocal p0 = 0\nCitizen.InvokeNative(0xB22B1D9F74095382, p0)"},{"name":"_0xB38C256498748413","hash":"0xB38C256498748413","build":"1207","ret":"void","comment":"","research":null,"params":[],"lua":"-- 0xB38C256498748413 · build 1207\nCitizen.InvokeNative(0xB38C256498748413)"},{"name":"_0xC81A9E2C8EFD28D5","hash":"0xC81A9E2C8EFD28D5","build":"1207","ret":"void","comment":"","research":null,"params":[{"name":"p0","type":"Any","out":false}],"lua":"-- 0xC81A9E2C8EFD28D5 · build 1207\nlocal p0 = 0\nCitizen.InvokeNative(0xC81A9E2C8EFD28D5, p0)"},{"name":"_0xDA801F7F6A5278D3","hash":"0xDA801F7F6A5278D3","build":"1207","ret":"BOOL","comment":"_NETWORK_GET_* or _NETWORK_IS_*","research":null,"params":[{"name":"player","type":"Player","out":false}],"lua":"-- 0xDA801F7F6A5278D3 · build 1207\nlocal player = PlayerId()\nlocal result = Citizen.InvokeNative(0xDA801F7F6A5278D3, player, Citizen.ResultAsInteger())"},{"name":"_0xE4C64CD37CB176AA","hash":"0xE4C64CD37CB176AA","build":"1207","ret":"Any","comment":"","research":null,"params":[{"name":"p0","type":"int","out":false}],"lua":"-- 0xE4C64CD37CB176AA · build 1207\nlocal p0 = 0\nlocal result = Citizen.InvokeNative(0xE4C64CD37CB176AA, p0, Citizen.ResultAsInteger())"},{"name":"_0xEE4F20004D0288B7","hash":"0xEE4F20004D0288B7","build":"1207","ret":"void","comment":"","research":null,"params":[],"lua":"-- 0xEE4F20004D0288B7 · build 1207\nCitizen.InvokeNative(0xEE4F20004D0288B7)"},{"name":"_0xFA7C5B7E087A4CEB","hash":"0xFA7C5B7E087A4CEB","build":"1207","ret":"Any","comment":"","research":null,"params":[],"lua":"-- 0xFA7C5B7E087A4CEB · build 1207\nlocal result = Citizen.InvokeNative(0xFA7C5B7E087A4CEB, Citizen.ResultAsInteger())"},{"name":"_NETWORK_GET_GANG_LEADER_HANDLE","hash":"0xCE88A261DCBBA0D9","build":"1207","ret":"BOOL","comment":"","research":null,"params":[{"name":"gangId","type":"Any","out":false},{"name":"gamerHandle","type":"Any*","out":true}],"lua":"-- 0xCE88A261DCBBA0D9 · build 1207\nlocal gangId = 0\nlocal result, gamerHandle = NetworkGetGangLeaderHandle(gangId)"},{"name":"_NETWORK_GET_GANG_MEMBERS","hash":"0xD1BF325C8252A982","build":"1207","ret":"int","comment":"","research":null,"params":[{"name":"gangId","type":"Any","out":false},{"name":"memberHandles","type":"Any*","out":true}],"lua":"-- 0xD1BF325C8252A982 · build 1207\nlocal gangId = 0\nlocal result, memberHandles = NetworkGetGangMembers(gangId)"},{"name":"_NETWORK_GET_GANG_PRIVACY","hash":"0x9970AE8C3D706139","build":"1207","ret":"int","comment":"","research":null,"params":[],"lua":"-- 0x9970AE8C3D706139 · build 1207\nlocal result = NetworkGetGangPrivacy()"},{"name":"_NETWORK_GET_GANG_SIZE","hash":"0x853B0FA4D8732C57","build":"1207","ret":"int","comment":"","research":null,"params":[{"name":"gangId","type":"Any","out":false}],"lua":"-- 0x853B0FA4D8732C57 · build 1207\nlocal gangId = 0\nlocal result = NetworkGetGangSize(gangId)"},{"name":"_NETWORK_IS_GANG_MEMBER","hash":"0x9BE7DCB22D32CCBE","build":"1207","ret":"BOOL","comment":"","research":null,"params":[{"name":"gangId","type":"Any","out":false},{"name":"player","type":"Player","out":false}],"lua":"-- 0x9BE7DCB22D32CCBE · build 1207\nlocal gangId = 0\nlocal player = PlayerId()\nlocal result = NetworkIsGangMember(gangId, player)"},{"name":"_NETWORK_IS_GANG_OPEN","hash":"0xFCF96CCBD81B24C8","build":"1207","ret":"BOOL","comment":"","research":null,"params":[{"name":"gangId","type":"Any","out":false}],"lua":"-- 0xFCF96CCBD81B24C8 · build 1207\nlocal gangId = 0\nlocal result = NetworkIsGangOpen(gangId)"},{"name":"_NETWORK_IS_IN_MY_GANG","hash":"0x81FB74C83C2ED69F","build":"1207","ret":"BOOL","comment":"","research":null,"params":[{"name":"player","type":"Player","out":false}],"lua":"-- 0x81FB74C83C2ED69F · build 1207\nlocal player = PlayerId()\nlocal result = NetworkIsInMyGang(player)"},{"name":"_NETWORK_KICK_GANG_MEMBER","hash":"0xCD9E2D9BC52FD80F","build":"1207","ret":"void","comment":"banTimeSeconds is 120 in R* Scripts","research":null,"params":[{"name":"player","type":"Player","out":false},{"name":"banTimeSeconds","type":"int","out":false}],"lua":"-- 0xCD9E2D9BC52FD80F · build 1207\nlocal player = PlayerId()\nlocal banTimeSeconds = 0\nNetworkKickGangMember(player, banTimeSeconds)"},{"name":"_NETWORK_LEAVE_GANG","hash":"0x0A04A07BC3074EDB","build":"1207","ret":"void","comment":"","research":null,"params":[{"name":"disband","type":"BOOL","out":false}],"lua":"-- 0x0A04A07BC3074EDB · build 1207\nlocal disband = true\nNetworkLeaveGang(disband)"},{"name":"_NETWORK_REQUEST_GANG_JOIN","hash":"0xC0474C8BCF6787AD","build":"1207","ret":"BOOL","comment":"Returns true if join succeeded, false if failed.","research":null,"params":[{"name":"gangId","type":"Any","out":false}],"lua":"-- 0xC0474C8BCF6787AD · build 1207\nlocal gangId = 0\nlocal result = NetworkRequestGangJoin(gangId)"},{"name":"_NETWORK_SET_GANG_PRIVACY","hash":"0xC5BF29F4035277C2","build":"1207","ret":"BOOL","comment":"","research":null,"params":[{"name":"privacyType","type":"int","out":false}],"lua":"-- 0xC5BF29F4035277C2 · build 1207\nlocal privacyType = 0\nlocal result = NetworkSetGangPrivacy(privacyType)"},{"name":"_NETWORK_SET_GANG_SIZE","hash":"0x833D8268D51B4522","build":"1207","ret":"BOOL","comment":"","research":null,"params":[{"name":"size","type":"int","out":false}],"lua":"-- 0x833D8268D51B4522 · build 1207\nlocal size = 0\nlocal result = NetworkSetGangSize(size)"},{"name":"_NETWORK_START_GANG","hash":"0xD1A226F2E05E58FC","build":"1207","ret":"void","comment":"openStatus = true -> sets privacyType = 2 (PUBLIC_ADVERTISED)\nopenStatus = false -> sets privacyType = 1 (INVITE_ONLY)\n\ncampSize: NET_CAMP_SIZE_SMALLEST = 4, NET_CAMP_SIZE_LARGEST = 7","research":null,"params":[{"name":"openStatus","type":"BOOL","out":false},{"name":"campSize","type":"int","out":false}],"lua":"-- 0xD1A226F2E05E58FC · build 1207\nlocal openStatus = true\nlocal campSize = 0\nNetworkStartGang(openStatus, campSize)"}]